bloggy/__init__.py
bloggy/agent.py
bloggy/build.py
bloggy/config.py
bloggy/core.py
bloggy/helpers.py
bloggy/layout_helpers.py
bloggy/main.py
bloggy/static/scripts.js
bloggy/static/sidenote.css
bloggy-0.3.4.dist-info/licenses/LICENSE
bloggy-0.3.4.dist-info/METADATA
bloggy-0.3.4.dist-info/WHEEL
bloggy-0.3.4.dist-info/entry_points.txt
bloggy-0.3.4.dist-info/top_level.txt
bloggy-0.3.4.dist-info/RECORD
