Metadata-Version: 2.4
Name: bloggy
Version: 0.3.4
Summary: A lightweight, elegant blogging platform built with FastHTML
Home-page: https://github.com/yeshwanth/bloggy
Author: Yeshwanth
Author-email: 
License: Apache-2.0
Project-URL: Homepage, https://github.com/yeshwanth/bloggy
Project-URL: Repository, https://github.com/yeshwanth/bloggy
Project-URL: Issues, https://github.com/yeshwanth/bloggy/issues
Keywords: fasthtml,blog,markdown,htmx,mermaid,sidenotes
Classifier: Development Status :: 4 - Beta
Classifier: Intended Audience :: Developers
Classifier: License :: OSI Approved :: Apache Software License
Classifier: Programming Language :: Python :: 3
Classifier: Programming Language :: Python :: 3.10
Classifier: Programming Language :: Python :: 3.11
Classifier: Programming Language :: Python :: 3.12
Classifier: Framework :: FastAPI
Classifier: Topic :: Internet :: WWW/HTTP :: Dynamic Content
Classifier: Topic :: Software Development :: Libraries :: Python Modules
Requires-Python: >=3.9
License-File: LICENSE
Requires-Dist: python-fasthtml>=0.6.9
Requires-Dist: mistletoe>=1.4.0
Requires-Dist: python-frontmatter>=1.1.0
Requires-Dist: uvicorn>=0.30.0
Requires-Dist: monsterui>=0.0.37
Requires-Dist: pylogue>=0.3
Provides-Extra: dev
Requires-Dist: pytest>=8.0.0; extra == "dev"
Requires-Dist: black>=24.0.0; extra == "dev"
Requires-Dist: ruff>=0.5.0; extra == "dev"
Provides-Extra: auth
Requires-Dist: authlib>=1.3.0; extra == "auth"
Dynamic: home-page
Dynamic: license-file
Dynamic: requires-python
